includex.py
docs/macros.py
mkdocs_macros_includex-0.0.6.dist-info/METADATA
mkdocs_macros_includex-0.0.6.dist-info/WHEEL
mkdocs_macros_includex-0.0.6.dist-info/licenses/LICENSE
mkdocs_macros_includex-0.0.6.dist-info/RECORD
