Metadata-Version: 2.1
Name: mkdocs-macros-includex
Version: 0.0.6
Summary: Provides the `includex` macro for more flexible includes.
Author-email: Jannis Mainczyk <jmainczyk@gmail.com>
License-Expression: MIT
License-File: LICENSE
Requires-Python: >=3.7
Provides-Extra: pygments
Requires-Dist: pygments; extra == 'pygments'
